Workbook

Sheet Dashboard
E1: HK | H1: AL
A2: TOTAL | C2: 1 | E2: =F4+F11+F19+F22+F23+F20+F21 -> 429283.39 | H2: =I4+I11+I19+I22+I23+I20+I21 -> 537912.89
A3: Category | B3: Currency | C3: Percent | D3: Target | E3: Target | F3: Actual | G3: Actual % | H3: Target | I3: Actual | J3: Actual % | K3: Actual Total | L3: Actual % of Total | N3: Currency
A4: Global Triads (the strategic core) | C4: 0.4 | D4: =$G$42*C4 -> 386878.51 | E4: =$E$2*C4 -> 171713.36 | F4: {=SUMPRODUCT(SUMIFS([1]PositionsHK!V:V,[1]PositionsHK!F:F,GlobalETF!A:A))} -> 147329.99 | G4: =F4/E4 -> 0.85799956 | H4: =$H$2*C4 -> 215165.16 | I4: {=SUMPRODUCT(SUMIFS([1]PositionsAL!V:V,[1]PositionsAL!F:F,GlobalETF!A:A))} -> 226383.72 | J4: =I4/H4 -> 1.0521393 | K4: =F4+I4 -> 373713.7 | L4: Core | M4: =K4/$G$42 -> 0.38638868
A5: China CSI300 (82846) | B5: CNY | C5: 0.05 | D5: =$D$4*C5 -> 19343.926 | E5: =$E$4*C5 -> 8585.6679 | F5: =SUMIFS([1]PositionsHK!V:V,[1]PositionsHK!F:F,"82846") -> 13648.848 | G5: =F5/E5 -> 1.5897247 | H5: =$H$4*C5 -> 10758.258 | I5: =SUMIFS([1]PositionsAL!V:V,[1]PositionsAL!F:F,"82846") -> 9099.232 | J5: =I5/H5 -> 0.84579047 | K5: =F5+I5 -> 22748.08 | N5: =K5 -> 22748.08 | O5: =B5 -> CNY
A6: DHL (dividend) | B6: EUR | C6: 0.05 | D6: =$D$4*C6 -> 19343.926 | E6: =$E$4*C6 -> 8585.6679 | F6: =SUMIFS([1]PositionsHK!V:V,[1]PositionsHK!F:F,"DHL") -> 0 | G6: =F6/E6 -> 0 | H6: =$H$4*C6 -> 10758.258 | I6: =SUMIFS([1]PositionsAL!V:V,[1]PositionsAL!F:F,"DHL") -> 51433.585 | J6: =I6/H6 -> 4.780847 | K6: =F6+I6 -> 51433.585 | N6: =K6 -> 51433.585 | O6: =B6 -> EUR
A7: ES3 (singapore banks) | B7: SGD | C7: 0.05 | D7: =$D$4*C7 -> 19343.926 | E7: =$E$4*C7 -> 8585.6679 | F7: =SUMIFS([1]PositionsHK!V:V,[1]PositionsHK!F:F,"ES3") -> 30137.952 | G7: =F7/E7 -> 3.510263 | H7: =$H$4*C7 -> 10758.258 | I7: =SUMIFS([1]PositionsAL!V:V,[1]PositionsAL!F:F,"ES3") -> 37672.44 | J7: =I7/H7 -> 3.5017231 | K7: =F7+I7 -> 67810.392 | N7: =K7 -> 67810.392 | O7: =B7 -> SGD
A8: VWRA (VT, incl. EM) | B8: USD | C8: 0.75 | D8: =$D$4*C8 -> 290158.89 | E8: =$E$4*C8 -> 128785.02 | F8: =SUMIFS([1]PositionsHK!V:V,[1]PositionsHK!F:F,"VWRA") -> 83910 | G8: =F8/E8 -> 0.65155094 | H8: =$H$4*C8 -> 161373.87 | I8: =SUMIFS([1]PositionsAL!V:V,[1]PositionsAL!F:F,"VWRA") -> 100692 | J8: =I8/H8 -> 0.6239672 | K8: =F8+I8 -> 184602 | N8: =K8 -> 184602 | O8: =B8 -> USD
A10: XMME (EM, unhedged) - india 18% | B10: CHF | C10: 0.1 | D10: =$D$4*C10 -> 38687.851 | E10: =$E$4*C10 -> 17171.336 | F10: =SUMIFS([1]PositionsHK!V:V,[1]PositionsHK!F:F,"XMME") -> 19633.185 | G10: =F10/E10 -> 1.1433697 | H10: =$H$4*C10 -> 21516.516 | I10: =SUMIFS([1]PositionsAL!V:V,[1]PositionsAL!F:F,"XMME") -> 27486.459 | J10: =I10/H10 -> 1.2774586 | K10: =F10+I10 -> 47119.644 | N10: =K10 -> 47119.644 | O10: =B10 -> CHF
A11: Four Horsemen (growth engine) | C11: 0.2 | D11: =$G$42*C11 -> 193439.26 | E11: =$E$2*C11 -> 85856.679 | F11: {=SUMPRODUCT(SUMIFS([1]PositionsHK!V:V,[1]PositionsHK!F:F,GrowthEngine!A:A))} -> 49202.457 | G11: =F11/E11 -> 0.57307664 | H11: =$H$2*C11 -> 107582.58 | I11: {=SUMPRODUCT(SUMIFS([1]PositionsAL!V:V,[1]PositionsAL!F:F,GrowthEngine!A:A))} -> 59096.748 | J11: =I11/H11 -> 0.54931522 | K11: =F11+I11 -> 108299.2 | L11: Growth | M11: =K11/$G$42 -> 0.11197231
A13: EQCH (QQQ, hedged) | B13: CHF | C13: 0.6 | D13: =$D$11*C13 -> 116063.55 | E13: =$E$11*C13 -> 51514.007 | F13: =SUMIFS([1]PositionsHK!V:V,[1]PositionsHK!F:F,"EQCH") -> 19729.85 | G13: =F13/E13 -> 0.38299972 | H13: =$H$11*C13 -> 64549.547 | I13: =SUMIFS([1]PositionsAL!V:V,[1]PositionsAL!F:F,"EQCH") -> 24662.313 | J13: =I13/H13 -> 0.38206795 | K13: =F13+I13 -> 44392.163 | N13: =K13 -> 44392.163 | O13: =B13 -> CHF
A14: CBUK (CQQQ, unhedged) | B14: CHF | C14: 0.1 | D14: =$D$11*C14 -> 19343.926 | E14: =$E$11*C14 -> 8585.6679 | F14: =SUMIFS([1]PositionsHK!V:V,[1]PositionsHK!F:F,"CBUK") -> 9923.6564 | G14: =F14/E14 -> 1.1558398 | H14: =$H$11*C14 -> 10758.258 | I14: =SUMIFS([1]PositionsAL!V:V,[1]PositionsAL!F:F,"CBUK") -> 14885.485 | J14: =I14/H14 -> 1.3836334 | K14: =F14+I14 -> 24809.141 | N14: =K14 -> 24809.141 | O14: =B14 -> CHF
A15: China Robotics (9807.HK) | B15: USD | C15: 0.1 | D15: =$D$11*C15 -> 19343.926 | E15: =$E$11*C15 -> 8585.6679 | F15: =SUMIFS([1]PositionsHK!V:V,[1]PositionsHK!F:F,"9807") -> 7735 | G15: =F15/E15 -> 0.90092001 | H15: =$H$11*C15 -> 10758.258 | I15: =SUMIFS([1]PositionsAL!V:V,[1]PositionsAL!F:F,"9807") -> 8508.5 | J15: =I15/H15 -> 0.79088084 | K15: =F15+I15 -> 16243.5 | N15: =K15 -> 16243.5 | O15: =B15 -> USD
A16: Energy (INRA) | B16: USD | C16: 0.1 | D16: =$D$11*C16 -> 19343.926 | E16: =$E$11*C16 -> 8585.6679 | F16: =SUMIFS([1]PositionsHK!V:V,[1]PositionsHK!F:F,"INRA") -> 10435.35 | G16: =F16/E16 -> 1.2154384 | H16: =$H$11*C16 -> 10758.258 | I16: =SUMIFS([1]PositionsAL!V:V,[1]PositionsAL!F:F,"INRA") -> 10435.35 | J16: =I16/H16 -> 0.96998511 | K16: =F16+I16 -> 20870.7 | N16: =K16 -> 20870.7 | O16: =B16 -> USD
A17: Energy (GRDU) | B17: USD | C17: 0.1 | D17: =$D$11*C17 -> 19343.926 | E17: =$E$11*C17 -> 8585.6679 | F17: =SUMIFS([1]PositionsHK!V:V,[1]PositionsHK!F:F,"GRDU") -> 9113.6 | G17: =F17/E17 -> 1.0614899 | H17: =$H$11*C17 -> 10758.258 | I17: =SUMIFS([1]PositionsAL!V:V,[1]PositionsAL!F:F,"GRDU") -> 9113.6 | J17: =I17/H17 -> 0.847126 | K17: =F17+I17 -> 18227.2 | N17: =K17 -> 18227.2 | O17: =B17 -> USD
A19: Cash Cow (income Strategy, wheel/CSPs/CC/callOpts) | B19: USD | C19: 0.15 | D19: =$G$42*C19 -> 145079.44 | E19: =$E$2*C19 -> 64392.509 | F19: {=SUMPRODUCT(SUMIFS([1]PositionsHK!V:V,[1]PositionsHK!F:F,IncomeStrategy!A:A))+SUMIFS([1]PositionsHK!V:V,[1]PositionsHK!D:D,"OPT")-SUMIFS([1]PositionsHK!V:V,[1]PositionsHK!D:D,"OPT",[1]PositionsHK!F:F,"SPY*")-SUMIFS([1]PositionsHK!V:V,[1]PositionsHK!D:D,"OPT",[1]PositionsHK!F:F,"QQQ*")+SUMIFS([1]PositionsHK!V:V,[1]PositionsHK!D:D,"FOP")-SUMIFS([1]PositionsHK!V:V,[1]PositionsHK!D:D,"FOP",[1]PositionsHK!F:F,"SPY*")-SUMIFS([1]PositionsHK!V:V,[1]PositionsHK!D:D,"FOP",[1]PositionsHK!F:F,"QQQ*")} -> 38310.83 | G19: =F19/E19 -> 0.59495787 | H19: =$H$2*C19 -> 80686.934 | I19: {=SUMPRODUCT(SUMIFS([1]PositionsAL!V:V,[1]PositionsAL!F:F,IncomeStrategy!A:A))+SUMIFS([1]PositionsAL!V:V,[1]PositionsAL!D:D,"OPT")-SUMIFS([1]PositionsAL!V:V,[1]PositionsAL!D:D,"OPT",[1]PositionsAL!F:F,"SPY*")-SUMIFS([1]PositionsAL!V:V,[1]PositionsAL!D:D,"OPT",[1]PositionsAL!F:F,"QQQ*")+SUMIFS([1]PositionsAL!V:V,[1]PositionsAL!D:D,"FOP")-SUMIFS([1]PositionsAL!V:V,[1]PositionsAL!D:D,"FOP",[1]PositionsAL!F:F,"SPY*")-SUMIFS([1]PositionsAL!V:V,[1]PositionsAL!D:D,"FOP",[1]PositionsAL!F:F,"QQQ*")} -> 56057.89 | J19: =I19/H19 -> 0.69475796 | K19: =F19+I19 -> 94368.72 | L19: Income | M19: =K19/$G$42 -> 0.097569357 | N19: =K19 -> 94368.72 | O19: =B19 -> USD
A20: The Alpha (theme stocks) | B20: USD | C20: 0.03 | D20: =$G$42*C20 -> 29015.889 | E20: =$E$2*C20 -> 12878.502 | F20: {=SUMIFS([1]PositionsHK!V:V,[1]PositionsHK!D:D,"STK")-SUMPRODUCT(SUMIFS([1]PositionsHK!V:V,[1]PositionsHK!D:D,"STK",[1]PositionsHK!F:F,GlobalETF!A:A))-SUMPRODUCT(SUMIFS([1]PositionsHK!V:V,[1]PositionsHK!D:D,"STK",[1]PositionsHK!F:F,GrowthEngine!A:A))-SUMPRODUCT(SUMIFS([1]PositionsHK!V:V,[1]PositionsHK!D:D,"STK",[1]PositionsHK!F:F,IncomeStrategy!A:A))-SUMPRODUCT(SUMIFS([1]PositionsHK!V:V,[1]PositionsHK!D:D,"STK",[1]PositionsHK!F:F,Gold!A:A))} -> 19545.766 | G20: =F20/E20 -> 1.517705 | H20: =$H$2*C20 -> 16137.387 | I20: {=SUMIFS([1]PositionsAL!V:V,[1]PositionsAL!D:D,"STK")-SUMPRODUCT(SUMIFS([1]PositionsAL!V:V,[1]PositionsAL!D:D,"STK",[1]PositionsAL!F:F,GlobalETF!A:A))-SUMPRODUCT(SUMIFS([1]PositionsAL!V:V,[1]PositionsAL!D:D,"STK",[1]PositionsAL!F:F,GrowthEngine!A:A))-SUMPRODUCT(SUMIFS([1]PositionsAL!V:V,[1]PositionsAL!D:D,"STK",[1]PositionsAL!F:F,IncomeStrategy!A:A))-SUMPRODUCT(SUMIFS([1]PositionsAL!V:V,[1]PositionsAL!D:D,"STK",[1]PositionsAL!F:F,Gold!A:A))} -> 21674.226 | J20: =I20/H20 -> 1.3431063 | K20: =F20+I20 -> 41219.992 | L20: Theme | M20: =K20/$G$42 -> 0.042618021 | N20: =K20 -> 41219.992 | O20: =B20 -> USD
A21: The Omega (insurance, SPY and QQQ bear spreads) | B21: USD | C21: 0.02 | D21: =$G$42*C21 -> 19343.926 | E21: =$E$2*C21 -> 8585.6679 | F21: =SUMIFS([1]PositionsHK!V:V,[1]PositionsHK!F:F,"SPY*",[1]PositionsHK!D:D,"OPT")+SUMIFS([1]PositionsHK!V:V,[1]PositionsHK!F:F,"SPY*",[1]PositionsHK!D:D,"FOP")+SUMIFS([1]PositionsHK!V:V,[1]PositionsHK!F:F,"QQQ*",[1]PositionsHK!D:D,"OPT")+SUMIFS([1]PositionsHK!V:V,[1]PositionsHK!F:F,"QQQ*",[1]PositionsHK!D:D,"FOP") -> 8700.92 | G21: =F21/E21 -> 1.0134238 | H21: =H2*C21 -> 10758.258 | I21: =SUMIFS([1]PositionsAL!V:V,[1]PositionsAL!F:F,"SPY*",[1]PositionsAL!D:D,"OPT")+SUMIFS([1]PositionsAL!V:V,[1]PositionsAL!F:F,"SPY*",[1]PositionsAL!D:D,"FOP")+SUMIFS([1]PositionsAL!V:V,[1]PositionsAL!F:F,"QQQ*",[1]PositionsAL!D:D,"OPT")+SUMIFS([1]PositionsAL!V:V,[1]PositionsAL!F:F,"QQQ*",[1]PositionsAL!D:D,"FOP") -> 8700.92 | J21: =I21/H21 -> 0.80876663 | K21: =F21+I21 -> 17401.84 | L21: Insurance | M21: =K21/$G$42 -> 0.017992046 | N21: =K21 -> 17401.84 | O21: =B21 -> USD
A22: The Vault (GSD, Gold) | B22: SGD | C22: 0.1 | D22: =$G$42*C22 -> 96719.629 | E22: =$E$2*C22 -> 42928.339 | F22: {=SUMPRODUCT(SUMIFS([1]PositionsHK!V:V,[1]PositionsHK!F:F,Gold!A:A))} -> 41199.405 | G22: =F22/E22 -> 0.95972511 | H22: =$H$2*C22 -> 53791.289 | I22: {=SUMPRODUCT(SUMIFS([1]PositionsAL!V:V,[1]PositionsAL!F:F,Gold!A:A))} -> 41199.405 | J22: =I22/H22 -> 0.7659122 | K22: =F22+I22 -> 82398.81 | L22: Gold | M22: =K22/$G$42 -> 0.085193472 | N22: =K22 -> 82398.81 | O22: =B22 -> SGD
A23: The War Chest (Cash) | B23: USD | C23: 0.05 | D23: =$G$42*C23 -> 48359.814 | E23: =$E$2*C23 -> 21464.17 | F23: =[1]Summary!$C$2 -> $124,994.03 | G23: =F23/E23 -> 5.8233806 | H23: =$H$2*C23 -> 26895.645 | I23: =[1]Summary!$C$3 -> $124,799.99 | J23: =I23/H23 -> 4.6401561 | K23: =F23+I23 -> 249794.02 | L23: Cash | M23: =K23/$G$42 -> 0.25826611
C24: =C4+C11+C19+C20+C21+C22+C23 -> 0.95
H40: Cash vs Invested | K40: Currency | N40: Portfolio
G41: Total | J41: CurrencyPrimary | K41: Total Value USD
G42: =E2+H2 -> 967196.29 | J42: USD | K42: =SUMIF(B4:B23, Query__2[[#This Row],[CurrencyPrimary]], N4:N23) -> 392933.95
G43: Invested | H43: =G44/G42 -> 0.74173389 | J43: CHF | K43: =SUMIF(B4:B23, Query__2[[#This Row],[CurrencyPrimary]], N4:N23) -> 116320.95
G44: =G42-G46 -> 717402.27 | J44: EUR | K44: =SUMIF(B4:B23, Query__2[[#This Row],[CurrencyPrimary]], N4:N23) -> 51433.585
G45: Cash | H45: =G46/G42 -> 0.25826611 | J45: SGD | K45: =SUMIF(B4:B23, Query__2[[#This Row],[CurrencyPrimary]], N4:N23) -> 150209.2
G46: =F23+I23 -> 249794.02 | J46: CNY | K46: =SUMIF(B4:B23, Query__2[[#This Row],[CurrencyPrimary]], N4:N23) -> 22748.08
B51: Target | C51: Actual
A52: =A4 -> Global Triads (the strategic core) | B52: =D4 -> 386878.51 | C52: =K4 -> 373713.7
A53: =A11 -> Four Horsemen (growth engine) | B53: =D11 -> 193439.26 | C53: =K11 -> 108299.2
A54: =A19 -> Cash Cow (income Strategy, wheel/CSPs/CC/callOpts) | B54: =D19 -> 145079.44 | C54: =K19 -> 94368.72
A55: =A20 -> The Alpha (theme stocks) | B55: =D20 -> 29015.889 | C55: =K20 -> 41219.992
A56: =A21 -> The Omega (insurance, SPY and QQQ bear spreads) | B56: =D21 -> 19343.926 | C56: =K21 -> 17401.84
A57: =A22 -> The Vault (GSD, Gold) | B57: =D22 -> 96719.629 | C57: =K22 -> 82398.81
A58: =A23 -> The War Chest (Cash) | B58: =D23 -> 48359.814 | C58: =K23 -> 249794.02

Sheet GlobalETF
A1: Ticker | B1: Currency | C1: Focus and Sector | D1: Expense Ratio | E1: Investment Strategy Profile | F1: AUM | G1: 1 Year Returns
A2: 82846 | B2: CNY | C2: China Large & Mid-Cap Equities | D2: 0.0038 | E2: CSI 300 Index | F2: ~CNY 1.45B | G2: -0.0635
A3: DHL | B3: EUR | C3: Deutsche Post AG - logistics/freight) | D3: N/A | E3: integrated freight & logistics company. Dividend yield ~4.5% | F3: N/A | G3: +29.64%
A4: ES3 | B4: SGD | C4: Singapore Blue-Chip Equities | D4: 0.30% | E4: Straits Times Index 30 Singapore companies including DBS, OCBC, UOB | F4: ~SGD 2.4B | G4: +34.03%
A5: VWRA | B5: USD | C5: Global All-World Equities | D5: 0.19% | E5: Developed + Emerging Markets, ~3,900 holdings across 50 countries | F5: ~USD 51.5B | G5: +22.49%
A6: WORLD | B6: CHF | C6: Developed Markets Equities | D6: 0.55% | E6: MSCI World Index, CHF-hedged, Large & Mid-Cap stocks 23 developed countries | F6: ~CHF 981M | G6: +13.29%
A7: XMME | B7: CHF | C7: Emerging Markets Equities | D7: 0.18% | E7: large & mid-cap stocks from 24 emerging market countries | F7: ~CHF 7.85B | G7: +14.72%

Sheet GrowthEngine
A1: Ticker | B1: Primary Exchange | C1: Country | D1: AUM (USD) | E1: Exp. Ratio | F1: 2025 Return | G1: Strategy Profile
A2: CSNDX | B2: USD | C2: Swiss | D2: 22.5b
A3: EQCH | B3: CHF | C3: Swiss | D3: 600m
A4: CBUK | B4: EUR | C4: Germany | D4: 2.1b
A5: INRA | B5: USD | C5: Netherlands | D5: 686m
A6: GRDU | B6: USD | C6: UK | D6: 1.0b

Sheet IncomeStrategy
A1: Ticker | B1: Category | C1: Best For | D1: 2026 Profile | E1: Why It Works?
A2: SPY | B2: Broad Market | C2: All Strategies | D2: Tracks S&P 500; ultra-liquid. | E2: Zero single-stock risk. Best for daily (0DTE) income and high-probability CSPs.
A3: ADBE | B3: Broad Tech | C3: Strangles | D3: High-margin AI creative tools. | E3: High share price; "smooth" price action with low spread slippage.
A4: AMD | B4: Broad Tech | C4: Strangles | D4: High retail volume; volatile. | E4: More affordable alternative to NVDA with high premium yield.
A5: CRM | B5: Broad Tech | C5: CSP / Wheel | D5: Subscription-based cash flow. | E5: Low downside risk due to recurring revenue stability.
A6: CSCO | B6: Broad Tech | C6: CSP / CC | D6: Defensive; bond-like value. | E6: Best for conservative traders looking for very high win rates.
A7: ORCL | B7: Broad Tech | C7: Strangles | D7: Massive cloud backlog. | E7: Higher volatility than MSFT, offering better Strangle returns.
A8: COST | B8: Consumer Staples | C8: CSP / Iron Condors | D8: Strong 8.2% net sales growth; high membership renewal rates; 20%+ digital sales growth in early FY2026. | E8: Differentiated membership model creates recurring revenue; bulk-buying value proposition is highly attractive to cost-conscious consumers during a recession.
A9: PEP | B9: Consumer Staples | C9: CSP / Dividend Growth | D9: Targeting 4-6% revenue growth; record productivity savings from automation; 53+ years of consecutive dividend increases. | E9: High nearly 4% yield provides a price floor; inelastic demand for snacks/beverages offers stable cash flow even in downturns.
A10: WMT | B10: Consumer Staples | C10: CSP / Wheel | D10: Global omnichannel leader with 27%+ e-commerce growth; expanding high-margin ad and membership streams. | E10: Defensive giant that gains market share during recessions as consumers "trade down" to its everyday low prices.
A11: XOM | B11: Energy | C11: CSP / Wheel | D11: Massive buybacks & FCF. | E11: Corporate buybacks create a "synthetic floor" for put sellers.
A12: JPM | B12: Financials | C12: CSP / Wheel | D12: Fortress balance sheet; 15% ROE. | E12: The gold standard for the "Wheel" strategy in financials.
... A23: QQQ | B23: Tech Index | C23: Strangles / CC | D23: Tracks Nasdaq 100; higher IV than SPY. | E23: Captures tech growth volatility without the risk of a single company failing.
A24: CMG
A25: NFLX
A26: SMH

Sheet Gold
A1: Ticker | B1: Category | C1: Best For | D1: 2026 Profile | E1: Why It Works?
A2: GSD | B2: Physical Gold ETF (Bullion-backed) | C2: Wealth preservation & Portfolio insurance | D2: Bullish Outlook: Price targets are pushing toward $5,000/oz by Q4 2026. | E2: Diversification: High liquidity and low correlation to traditional stocks.
A3: AEM | B3: Senior Tier-1 Gold Producer. Canada-based global miner with major operations in Canada (Detour Lake, Canadian Malartic), Australia (Fosterville), and Finland (Kittila). | C3: Stable Gold Exposure & Dividend Income. Ideal for "Buy and Hold" investors seeking safe-haven assets with consistent income; has paid a dividend every year since 1983. | D3: Bullish Growth. Median 12-month analyst price target is approximately $250.50, with high-end bull cases reaching $312 – $333 following a surge in gold prices to over $5,000/oz in early 2026. | E3: Low-Risk Jurisdictions & High Margins. Focuses on politically stable regions (Canada/Australia) to avoid resource nationalism. Boasts record-level profit margins (37.5%) and some of the industry's lowest All-In Sustaining Costs (AISC), ensuring profitability even if gold prices soften.

Sheet Todo
